ham/__init__.py
ham/binary_sensor.py
ham/button.py
ham/fan.py
ham/light.py
ham/manager.py
ham/number.py
ham/sensor.py
ham/switch.py
ham/things.py
ham/utils.py
hass_mqtt_things-0.5.9.dist-info/METADATA
hass_mqtt_things-0.5.9.dist-info/WHEEL
hass_mqtt_things-0.5.9.dist-info/licenses/LICENSE
hass_mqtt_things-0.5.9.dist-info/RECORD
