Metadata-Version: 2.1
Name: hass-mqtt-things
Version: 0.5.9
Summary: Library for rapid development of things to be integrated with Home Assistant through MQTT
Project-URL: Documentation, https://github.com/alexbarcelo/hass-mqtt-things#readme
Project-URL: Issues, https://github.com/alexbarcelo/hass-mqtt-things/issues
Project-URL: Source, https://github.com/alexbarcelo/hass-mqtt-things
Author-email: Alex Barcelo <alex@betarho.net>
License-Expression: Apache-2.0
License-File: LICENSE
Keywords: home automation,home-assistant,internet of things,iot,things
Classifier: Development Status :: 4 - Beta
Classifier: Intended Audience :: Developers
Classifier: License :: OSI Approved :: Apache Software License
Classifier: Programming Language :: Python :: 3 :: Only
Classifier: Programming Language :: Python :: 3.9
Classifier: Programming Language :: Python :: 3.10
Classifier: Programming Language :: Python :: 3.11
Classifier: Programming Language :: Python :: 3.12
Classifier: Topic :: Home Automation
Requires-Python: >=3.9
Requires-Dist: getmac
Requires-Dist: paho-mqtt
